Core/DateTimeFormats.py
Core/__init__.py
DateTimeFormatJKP/DateTimeFormatJKP.py
DateTimeFormatJKP/DateTimeFormats.py
DateTimeFormatJKP/__init__.py
DateTimeFormatJKP-0.1.7.dist-info/LICENSE
DateTimeFormatJKP-0.1.7.dist-info/METADATA
DateTimeFormatJKP-0.1.7.dist-info/WHEEL
DateTimeFormatJKP-0.1.7.dist-info/top_level.txt
DateTimeFormatJKP-0.1.7.dist-info/RECORD
