Metadata-Version: 2.1
Name: DateTimeFormatJKP
Version: 0.1.7
Summary: Library for robot framework
Home-page: https://github.com/praveenjkp/DateFormat
Author: Praveen Kumar Kanagaraj
Author-email: pk292695@gmail.com
License: apache 2.0 Software License
Download-URL: https://github.com/praveenjkp/DateFormat
Platform: UNKNOWN
Classifier: Development Status :: 2 - Pre-Alpha
Classifier: Environment :: Web Environment
Classifier: Framework :: Robot Framework :: Library
Classifier: Intended Audience :: Developers
Classifier: License :: OSI Approved :: Apache Software License
Classifier: Operating System :: OS Independent
Classifier: Programming Language :: Python :: 2.7
Classifier: Programming Language :: Python :: Implementation :: PyPy
Classifier: Topic :: Software Development :: Libraries :: Application Frameworks
Requires-Python: >= 2.7.10
Requires-Dist: robotframework (>=2.8.7)
Requires-Dist: robotframework-selenium2library (>=1.7.4)
